st_storage_handler/__init__.py
st_storage_handler/frontend/build/asset-manifest.json
st_storage_handler/frontend/build/bootstrap.min.css
st_storage_handler/frontend/build/index.html
st_storage_handler/frontend/build/precache-manifest.c2c4f6e3e6b7b4d0ba04059537fc62e3.js
st_storage_handler/frontend/build/service-worker.js
st_storage_handler/frontend/build/static/js/2.2c444e17.chunk.js
st_storage_handler/frontend/build/static/js/2.2c444e17.chunk.js.LICENSE.txt
st_storage_handler/frontend/build/static/js/2.2c444e17.chunk.js.map
st_storage_handler/frontend/build/static/js/main.bf335477.chunk.js
st_storage_handler/frontend/build/static/js/main.bf335477.chunk.js.map
st_storage_handler/frontend/build/static/js/runtime-main.c742f5d3.js
st_storage_handler/frontend/build/static/js/runtime-main.c742f5d3.js.map
st_storage_handler-0.0.1.dist-info/LICENSE
st_storage_handler-0.0.1.dist-info/METADATA
st_storage_handler-0.0.1.dist-info/WHEEL
st_storage_handler-0.0.1.dist-info/top_level.txt
st_storage_handler-0.0.1.dist-info/RECORD
