Metadata-Version: 2.1
Name: st-storage-handler
Version: 0.0.1
Summary: Streamlit Component for handling local storage
Author: 
Author-email: 
Requires-Python: >=3.6
License-File: LICENSE
Requires-Dist: streamlit (>=0.63)
